{
  "project_info": {
    "project_number": "538237330288",
    "project_id": "ecom-8177b",
    "storage_bucket": "ecom-8177b.appspot.com"
  },
  "client": [
    {
      "client_info": {
        "mobilesdk_app_id": "1:538237330288:android:32c54c0c853355bc4465b5",
        "android_client_info": {
          "package_name": "com.company.ecom"
        }
      },
      "oauth_client": [],
      "api_key": [
        {
          "current_key": "AIzaSyDIiYqac37XTdWkPvd0LvG4up0RrAFEOYk"
        }
      ],
      "services": {
        "appinvite_service": {
          "other_platform_oauth_client": []
        }
      }
    },
    {
      "client_info": {
        "mobilesdk_app_id": "1:538237330288:android:87614105ff0d67634465b5",
        "android_client_info": {
          "package_name": "com.company.sample"
        }
      },
      "oauth_client": [],
      "api_key": [
        {
          "current_key": "AIzaSyDIiYqac37XTdWkPvd0LvG4up0RrAFEOYk"
        }
      ],
      "services": {
        "appinvite_service": {
          "other_platform_oauth_client": []
        }
      }
    },
    {
      "client_info": {
        "mobilesdk_app_id": "1:538237330288:android:2667f6f89c57ebc44465b5",
        "android_client_info": {
          "package_name": "com.mycompany.newww"
        }
      },
      "oauth_client": [],
      "api_key": [
        {
          "current_key": "AIzaSyDIiYqac37XTdWkPvd0LvG4up0RrAFEOYk"
        }
      ],
      "services": {
        "appinvite_service": {
          "other_platform_oauth_client": []
        }
      }
    }
  ],
  "configuration_version": "1"
}